Metadata-Version: 2.0
Name: odoo10-addon-base-location-geonames-import
Version: 10.0.1.1.1
Summary: Import better zip entries from Geonames
Home-page: http://www.akretion.com
Author: Akretion,Agile Business Group,Antiun Ingeniería S.L.,Tecnativa,Odoo Community Association (OCA)
Author-email: support@odoo-community.org
License: AGPL-3
Platform: UNKNOWN
Classifier: Programming Language :: Python
Classifier: Framework :: Odoo
Classifier: License :: OSI Approved :: GNU Affero General Public License v3
Requires-Python: ~=2.7
Requires-Dist: odoo (<10.1dev,>=10.0)
Requires-Dist: odoo10-addon-base-location
Requires-Dist: requests
Requires-Dist: unicodecsv
